codemod_docker/__init__.py
codemod_docker-0.0.0a1.dist-info/METADATA
codemod_docker-0.0.0a1.dist-info/WHEEL
codemod_docker-0.0.0a1.dist-info/RECORD
