Metadata-Version: 2.4
Name: codemod-docker
Version: 0.0.0a1
Summary: coming soon
Author-email: Tim Hatch <tim@timhatch.com>
